SEEQ_EMATICA_ADDON_PCA/__init__.py
SEEQ_EMATICA_ADDON_PCA/_seeq_add_on.py
seeq_ematica_addon_pca-1.0.6.dist-info/licenses/LICENSE
seeq_ematica_addon_pca-1.0.6.dist-info/METADATA
seeq_ematica_addon_pca-1.0.6.dist-info/WHEEL
seeq_ematica_addon_pca-1.0.6.dist-info/top_level.txt
seeq_ematica_addon_pca-1.0.6.dist-info/RECORD
