Metadata-Version: 2.4
Name: SEEQ_EMATICA_ADDON_PCA
Version: 1.0.6
Summary: PCA Package for Seeq Addons
Author: Alessandro Robbiano
Author-email: alessandro.robbiano@e-matica.it
License: MIT
Classifier: Programming Language :: Python :: 3
Classifier: Operating System :: OS Independent
Requires-Python: >=3.6
License-File: LICENSE
Requires-Dist: ipyvuetify~=1.9.4
Requires-Dist: ipywidgets
Requires-Dist: IPython
Requires-Dist: ipywidgets
Requires-Dist: pandas
Requires-Dist: scikit-learn
Requires-Dist: seeq~=66.0.0.dev20241031
Requires-Dist: seeq-spy
Requires-Dist: numpy
Requires-Dist: datetime
Requires-Dist: pytz
Requires-Dist: plotly
Requires-Dist: configparser_crypt
Dynamic: author
Dynamic: author-email
Dynamic: classifier
Dynamic: description
Dynamic: description-content-type
Dynamic: license
Dynamic: license-file
Dynamic: requires-dist
Dynamic: requires-python
Dynamic: summary
